blinker/__init__.py
blinker/_saferef.py
blinker/_utilities.py
blinker/base.py
blinker_alt-1.5.dist-info/DESCRIPTION.rst
blinker_alt-1.5.dist-info/METADATA
blinker_alt-1.5.dist-info/RECORD
blinker_alt-1.5.dist-info/WHEEL
blinker_alt-1.5.dist-info/metadata.json
blinker_alt-1.5.dist-info/top_level.txt
